spectrominer/__init__.py
spectrominer/corrections/__init__.py
spectrominer/corrections/experimental.py
spectrominer/corrections/theoretical.py
spectrominer/corrections/util.py
spectrominer/errors.py
spectrominer/parser/__init__.py
spectrominer/parser/analysis.py
spectrominer/parser/molecule_results.py
spectrominer/parser/parser.py
spectrominer/parser/util.py
spectrominer/ui/__init__.py
spectrominer/ui/app.py
spectrominer/ui/correction_wizard.py
spectrominer/ui/file_selector_frame.py
spectrominer/ui/main_frame.py
spectrominer/ui/popup.py
spectrominer-0.0.4.dist-info/entry_points.txt
spectrominer-0.0.4.dist-info/LICENSE
spectrominer-0.0.4.dist-info/WHEEL
spectrominer-0.0.4.dist-info/METADATA
spectrominer-0.0.4.dist-info/RECORD
